remote_graphcast/__init__.py
remote_graphcast/gcutils/__init__.py
remote_graphcast/gcutils/cdsutils.py
remote_graphcast/gcutils/constants.py
remote_graphcast/gcutils/inpututils.py
remote_graphcast/gcutils/log_config.py
remote_graphcast/gcutils/test_cdsutils.py
remote_graphcast/sdk/__init__.py
remote_graphcast/sdk/cli.py
remote_graphcast/sdk/remote_cast.py
remote_graphcast_runpod-0.0.23.dist-info/METADATA
remote_graphcast_runpod-0.0.23.dist-info/WHEEL
remote_graphcast_runpod-0.0.23.dist-info/top_level.txt
remote_graphcast_runpod-0.0.23.dist-info/RECORD
