Metadata-Version: 2.1
Name: remote-graphcast-runpod
Version: 0.0.23
Summary: Allows people without massive GPUs to easily run graphcast on remote runpod servers
Home-page: https://github.com/CisgenX/remote-graphcast.git
Author: Louka Ewington-Pitsos
Author-email: lewingtonpitsos@gmail.com
Classifier: Programming Language :: Python :: 3
Classifier: License :: OSI Approved :: MIT License
Classifier: Operating System :: OS Independent
Requires-Python: >=3.10
Requires-Dist: boto3
Requires-Dist: runpod
